bbdl/__init__.py
bbdl/bbdl.py
bbdl-2.0.5.dist-info/METADATA
bbdl-2.0.5.dist-info/WHEEL
bbdl-2.0.5.dist-info/licenses/LICENSE
bbdl-2.0.5.dist-info/RECORD
