Metadata-Version: 2.1
Name: bbdl
Version: 2.0.5
Summary: BBDL
License-File: LICENSE
Classifier: Operating System :: OS Independent
Classifier: Programming Language :: Python :: 3
Requires-Python: >=3.9
